odoo/addons/account_invoice_export_server_env/README.rst
odoo/addons/account_invoice_export_server_env/__init__.py
odoo/addons/account_invoice_export_server_env/__manifest__.py
odoo/addons/account_invoice_export_server_env/i18n/account_invoice_export_server_env.pot
odoo/addons/account_invoice_export_server_env/i18n/es.po
odoo/addons/account_invoice_export_server_env/i18n/it.po
odoo/addons/account_invoice_export_server_env/models/__init__.py
odoo/addons/account_invoice_export_server_env/models/transmit_method.py
odoo/addons/account_invoice_export_server_env/readme/CREDITS.md
odoo/addons/account_invoice_export_server_env/readme/DESCRIPTION.md
odoo/addons/account_invoice_export_server_env/static/description/icon.png
odoo/addons/account_invoice_export_server_env/static/description/index.html
odoo/addons/account_invoice_export_server_env/tests/__init__.py
odoo/addons/account_invoice_export_server_env/tests/test_transmit_method.py
odoo/addons/account_invoice_export_server_env/tests/testfiles/test/test.conf
odoo_addon_account_invoice_export_server_env-18.0.1.0.0.4.dist-info/METADATA
odoo_addon_account_invoice_export_server_env-18.0.1.0.0.4.dist-info/WHEEL
odoo_addon_account_invoice_export_server_env-18.0.1.0.0.4.dist-info/top_level.txt
odoo_addon_account_invoice_export_server_env-18.0.1.0.0.4.dist-info/RECORD
